streamlit_list_widget/__init__.py
streamlit_list_widget/frontend/build/asset-manifest.json
streamlit_list_widget/frontend/build/bootstrap.min.css
streamlit_list_widget/frontend/build/index.html
streamlit_list_widget/frontend/build/static/js/main.d65a2168.js
streamlit_list_widget/frontend/build/static/js/main.d65a2168.js.LICENSE.txt
streamlit_list_widget/frontend/build/static/js/main.d65a2168.js.map
streamlit_list_widget-0.1.11.dist-info/LICENSE
streamlit_list_widget-0.1.11.dist-info/METADATA
streamlit_list_widget-0.1.11.dist-info/WHEEL
streamlit_list_widget-0.1.11.dist-info/top_level.txt
streamlit_list_widget-0.1.11.dist-info/RECORD
