Metadata-Version: 2.1
Name: streamlit-list-widget
Version: 0.1.11
Summary: Streamlit component that allows you to do handle a list of clickable items
Home-page: 
Author: Marco Sanguineti
Author-email: marco.sanguineti.info@gmail.com
Requires-Python: >=3.7
License-File: LICENSE
Requires-Dist: streamlit>=0.63
Provides-Extra: devel
Requires-Dist: wheel; extra == "devel"
Requires-Dist: pytest==7.4.0; extra == "devel"
Requires-Dist: playwright==1.39.0; extra == "devel"
Requires-Dist: requests==2.31.0; extra == "devel"
Requires-Dist: pytest-playwright-snapshot==1.0; extra == "devel"
Requires-Dist: pytest-rerunfailures==12.0; extra == "devel"
